mwcli/__init__.py
mwcli/about.py
mwcli/errors.py
mwcli/router.py
mwcli/streamer.py
mwcli/files/__init__.py
mwcli/files/functions.py
mwcli/files/p7z.py
mwcli/files/tests/__init__.py
mwcli/files/tests/test_functions.py
mwcli/files/tests/test_p7z.py
mwcli-0.0.3.dist-info/LICENSE
mwcli-0.0.3.dist-info/METADATA
mwcli-0.0.3.dist-info/WHEEL
mwcli-0.0.3.dist-info/top_level.txt
mwcli-0.0.3.dist-info/RECORD
